pypyrus_runner/__init__.py
pypyrus_runner/job.py
pypyrus_runner/manager.py
pypyrus_runner/parser.py
pypyrus_runner/scheduler.py
pypyrus_runner-0.0.1.dist-info/LICENCE
pypyrus_runner-0.0.1.dist-info/METADATA
pypyrus_runner-0.0.1.dist-info/WHEEL
pypyrus_runner-0.0.1.dist-info/top_level.txt
pypyrus_runner-0.0.1.dist-info/RECORD
