Metadata-Version: 2.1
Name: pypyrus-runner
Version: 0.0.1
Summary: Python scheduler and job manager.
Home-page: https://github.com/t3eHawk/runner
Author: Timur Faradzhov
Author-email: timurfaradzhov@gmail.com
License: MIT
Platform: UNKNOWN
Classifier: Programming Language :: Python :: 3
Classifier: License :: OSI Approved :: MIT License
Classifier: Operating System :: OS Independent
Requires-Dist: pypyrus-tables (>=0.0.2)
Requires-Dist: pypyrus-logbook (>=0.0.2)
